ngw_contract_backtest/__init__.py
ngw_contract_backtest/ngw/__init__.py
ngw_contract_backtest/ngw/constants.py
ngw_contract_backtest/ngw/app_api/__init__.py
ngw_contract_backtest/ngw/app_api/common.py
ngw_contract_backtest/ngw/app_api/execee.py
ngw_contract_backtest/ngw/app_api/sendpro_api.py
ngw_contract_backtest/ngw/app_api/trace.py
ngw_contract_backtest/ngw/app_api/trade_api.py
ngw_contract_backtest/ngw/conn_sql/__init__.py
ngw_contract_backtest/ngw/conn_sql/conn_redis.py
ngw_contract_backtest/ngw/conn_sql/insert_sql.py
ngw_contract_backtest/ngw/conn_sql/select_sql.py
ngw_contract_backtest/ngw/context/__init__.py
ngw_contract_backtest/ngw/context/context.py
ngw_contract_backtest/ngw/data/__init__.py
ngw_contract_backtest/ngw/data/cache.py
ngw_contract_backtest/ngw/data/data_api.py
ngw_contract_backtest/ngw/report/__init__.py
ngw_contract_backtest/ngw/report/risk_metrics.py
ngw_contract_backtest/ngw/strategy/__init__.py
ngw_contract_backtest/ngw/strategy/strategy.py
ngw_contract_backtest/ngw/utils/__init__.py
ngw_contract_backtest/ngw/utils/data_util.py
ngw_contract_backtest/ngw/utils/date_util.py
ngw_contract_backtest/ngw/utils/exceptions.py
ngw_contract_backtest/ngw/utils/freq_util.py
ngw_contract_backtest/ngw/utils/log_util.py
ngw_contract_backtest/ngw/utils/print_util.py
ngw_contract_backtest/ngw/utils/thread_util.py
ngw_contract_backtest/ngw/utils/trade_time_util.py
ngw_contract_backtest/ngw/websocket/__init__.py
ngw_contract_backtest/ngw/websocket/websocketClient.py
ngw_contract_backtest-0.2.2.dist-info/METADATA
ngw_contract_backtest-0.2.2.dist-info/WHEEL
ngw_contract_backtest-0.2.2.dist-info/top_level.txt
ngw_contract_backtest-0.2.2.dist-info/RECORD
