Metadata-Version: 2.1
Name: ngw-contract-backtest
Version: 0.2.2
Summary: contract framework 022
Home-page: https://github.com/296348304/ngw_contract_backtest
Author: Wang Jian
Author-email: 296348304@qq.com
License: UNKNOWN
Platform: UNKNOWN
Classifier: Programming Language :: Python :: 3
Classifier: License :: OSI Approved :: MIT License
Classifier: Operating System :: OS Independent
Requires-Python: >=3.7
